biobb_io/__init__.py
biobb_io/py.typed
biobb_io/api/__init__.py
biobb_io/api/alphafold.py
biobb_io/api/api_binding_site.py
biobb_io/api/canonical_fasta.py
biobb_io/api/common.py
biobb_io/api/ideal_sdf.py
biobb_io/api/ligand.py
biobb_io/api/mddb.py
biobb_io/api/memprotmd_sim.py
biobb_io/api/memprotmd_sim_list.py
biobb_io/api/memprotmd_sim_search.py
biobb_io/api/mmcif.py
biobb_io/api/pdb.py
biobb_io/api/pdb_cluster_zip.py
biobb_io/api/pdb_variants.py
biobb_io/api/structure_info.py
biobb_io/test/__init__.py
biobb_io-5.2.0.dist-info/licenses/LICENSE
biobb_io-5.2.0.dist-info/METADATA
biobb_io-5.2.0.dist-info/WHEEL
biobb_io-5.2.0.dist-info/entry_points.txt
biobb_io-5.2.0.dist-info/top_level.txt
biobb_io-5.2.0.dist-info/RECORD
